Other Projects/shifter4bit/shifter4bit/shifter4bit.v
// ماژول شیفت‌دهنده 4 بیتی

module shifter4bit (
    input clk,          // ورودی کلاک
    input rst,          // ورودی ریست
    input [3:0] data_in, // داده ورودی
    input sel,          // ورودی انتخاب جهت شیفت (0: راست، 1: چپ)
    output [3:0] data_out // داده خروجی
);

    // رجیسترها برای ذخیره داده‌ها
    reg [3:0] reg1, reg2;

    // بلوک always فعال با لبه مثبت کلاک
    always @(posedge clk) begin
        if (rst) begin
            // در صورت ریست فعال، رجیسترها را با 0 مقداردهی اولیه می‌کنیم
            reg1 <= 0;
            reg2 <= 0;
        end else begin
            // در غیر این صورت، داده‌ها را بر اساس ورودی انتخاب به رجیسترها منتقل می‌کنیم
            reg1 <= data_in;
            if (sel) begin
                // شیفت چپ
                reg2 <= {reg1[2:0], 1'b0};
            end else begin
                // شیفت راست
                reg2 <= {1'b0, reg1[3:1]};
            end
        end
    end

    // خروجی شیفت‌دهنده
    assign data_out = reg2;

endmodule

Other Projects/shifter4bit/shifter4bit/shifter4bit_tb.v
`include "shifter4bit.v" // فراخوانی 
module shifter4bit_tb;
    // پورت‌های ورودی و خروجی
    reg clk = 0;
    reg rst;
    reg [3:0] data_in;
    reg sel;
    wire [3:0] data_out;

    // شیفت‌دهنده
    shifter4bit shifter (.clk(clk), .rst(rst), .data_in(data_in), .sel(sel), .data_out(data_out));

    // بلوک always برای تولید سیگنال‌های کلاک
    always #5 clk = ~clk; // فرکانس کلاک 200 مگاهرتز

    // بلوک initial برای تعریف وضعیت اولیه و تست‌های مختلف
    initial begin
        // تنظیم فایل خروجی VCD
        $dumpfile("shifter4bit.vcd");
        $dumpvars(0, shifter4bit_tb);

        // وضعیت اولیه
        rst = 1'b1;
        data_in = 4'b0000;
        sel = 1'b0;
        #10 rst = 1'b0; // ریست غیرفعال

        // تست‌های مختلف
        #20 data_in = 4'b0101; sel = 1'b0; // شیفت راست
        #20 data_in = 4'b1010; sel = 1'b1; // شیفت چپ
        #20 data_in = 4'b1111; sel = 1'b0; // شیفت راست
        #20 data_in = 4'b0001; sel = 1'b1; // شیفت چپ
        #20 $finish; // پایان شبیه‌سازی
    end

    // بلوک monitor برای نمایش مقادیر سیگنال‌ها
    initial begin
        $monitor("Time = %t : clk = %b, rst = %b, data_in = %b, sel = %b, data_out = %b", $time, clk, rst, data_in, sel, data_out);
    end
endmodule

Other Projects/shifter4bit/shifter4bit/shifter4bit.vcd
$date
	Tue Jun 04 03:09:59 2024
$end
$version
	Icarus Verilog
$end
$timescale
	1s
$end
$scope module shifter4bit_tb $end
$var wire 4 ! data_out [3:0] $end
$var reg 1 " clk $end
$var reg 4 # data_in [3:0] $end
$var reg 1 $ rst $end
$var reg 1 % sel $end
$scope module shifter $end
$var wire 1 " clk $end
$var wire 4 & data_in [3:0] $end
$var wire 4 ' data_out [3:0] $end
$var wire 1 $ rst $end
$var wire 1 % sel $end
$var reg 4 ( reg1 [3:0] $end
$var reg 4 ) reg2 [3:0] $end
$upscope $end
$upscope $end
$enddefinitions $end
#0
$dumpvars
bx )
bx (
bx '
b0 &
0%
1$
b0 #
0"
bx !
$end
#5
b0 !
b0 '
b0 )
b0 (
1"
#10
0"
0$
#15
1"
#20
0"
#25
1"
#30
0"
b101 #
b101 &
#35
b101 (
1"
#40
0"
#45
b10 !
b10 '
b10 )
1"
#50
0"
1%
b1010 #
b1010 &
#55
b1010 !
b1010 '
b1010 )
b1010 (
1"
#60
0"
#65
b100 !
b100 '
b100 )
1"
#70
0"
0%
b1111 #
b1111 &
#75
b101 !
b101 '
b101 )
b1111 (
1"
#80
0"
#85
b111 !
b111 '
b111 )
1"
#90
0"
1%
b1 #
b1 &
#95
b1110 !
b1110 '
b1110 )
b1 (
1"
#100
0"
#105
b10 !
b10 '
b10 )
1"
